reinfier/CONST.py
reinfier/Protocal.py
reinfier/Setting.py
reinfier/__init__.py
reinfier/algo/__init__.py
reinfier/algo/lib.py
reinfier/algo/multi.py
reinfier/algo/selector.py
reinfier/algo/single.py
reinfier/algo/tests/__init__.py
reinfier/algo/tests/test_single.py
reinfier/common/DNNP.py
reinfier/common/DRLP.py
reinfier/common/Feature.py
reinfier/common/NN.py
reinfier/common/__init__.py
reinfier/common/base_class.py
reinfier/common/type_aliases.py
reinfier/drlp/DRLPTransformer.py
reinfier/drlp/__init__.py
reinfier/drlp/auxiliary.py
reinfier/drlp/editor.py
reinfier/drlp/error.py
reinfier/drlp/lib.py
reinfier/drlp/parser.py
reinfier/interface/__init__.py
reinfier/interface/dnnv/__init__.py
reinfier/interface/dnnv/booter.py
reinfier/interface/docker/__init__.py
reinfier/interface/docker/docker.py
reinfier/interface/docker/tests/__init__.py
reinfier/interface/docker/tests/test_docker.py
reinfier/interface/marabou/__init__.py
reinfier/interface/marabou/booter.py
reinfier/interface/verisig/__init__.py
reinfier/interface/verisig/booter.py
reinfier/interpretor/__init__.py
reinfier/interpretor/lib.py
reinfier/interpretor/solver.py
reinfier/interpretor/tests/__init__.py
reinfier/interpretor/tests/test_solver.py
reinfier/nn/__init__.py
reinfier/nn/expander.py
reinfier/nn/lib.py
reinfier/nn/onnx_runner.py
reinfier/reintrainer/Reintrainer.py
reinfier/reintrainer/__init__.py
reinfier/res/__init__.py
reinfier/res/test01/drlp/test01_p1.drlp
reinfier/res/test01/nn/test01.onnx
reinfier/util/TimerGroup.py
reinfier/util/__init__.py
reinfier/util/data.py
reinfier/util/lib.py
reinfier/util/output_wrapper.py
reinfier-0.5.3.dist-info/LICENSE
reinfier-0.5.3.dist-info/WHEEL
reinfier-0.5.3.dist-info/METADATA
reinfier-0.5.3.dist-info/RECORD
