Metadata-Version: 2.1
Name: reinfier
Version: 0.5.3
Summary: Reinfier - A verification framework for deep reinforcement learning
Keywords: DRL,DNN,verification,interpretation
Author-email: Kurayuri <Kurayuri@outlook.com>
Requires-Python: >=3.10
Classifier: License :: OSI Approved :: MIT License
Requires-Dist: onnxruntime>=1.17.0
Requires-Dist: onnx>=1.16.0
Requires-Dist: astpretty>=2.1.0
Requires-Dist: astor>=0.8.1
Requires-Dist: yapf>=0.32.0
Requires-Dist: scipy>=1.10.1
Requires-Dist: torch>=2.1.0
Requires-Dist: docker>=6.1.3
Requires-Dist: pyyaml>=6.0.1
Requires-Dist: pytest>=7.4.3
Requires-Dist: onnx2torch>=1.5.13
Project-URL: Home, https://github.com/Kurayuri/Reinfier
